Moby_Land/__init__.py
Moby_Land/astro/__init__.py
Moby_Land/astro/conversions.py
Moby_Land/custom_logging/__init__.py
Moby_Land/custom_logging/clean_logger.py
Moby_Land/plotting/__init__.py
Moby_Land/plotting/plotting_styles.py
test_suite/__init__.py
Moby_Land-0.3.1.dist-info/LICENSE
Moby_Land-0.3.1.dist-info/METADATA
Moby_Land-0.3.1.dist-info/WHEEL
Moby_Land-0.3.1.dist-info/top_level.txt
Moby_Land-0.3.1.dist-info/RECORD
