Metadata-Version: 2.1
Name: Moby-Land
Version: 0.3.1
Summary: A place for all of my gadgets.
Author: Adam Boesky
Author-email: apboesky@gmail.com
Classifier: Programming Language :: Python :: 3
Classifier: License :: OSI Approved :: MIT License
Classifier: Operating System :: OS Independent
Requires-Python: >=3.11
License-File: LICENSE
Requires-Dist: matplotlib
Requires-Dist: numpy
